<?xml version="1.0" encoding="utf-8" standalone="yes"?>
<set xmlns:noNamespaceSchemaLocation="CardSet.xsd" name="DMD-24 Masters Chronicle Deck: Bolmeteus Returns" id="c1673485-a1a2-4cf1-a4e3-a3d65ec9d915" gameId="bb784fc6-fe21-4603-90d7-82c049908a74" gameVersion="3.0.0.0" version="2.0.0.0">
	<packaging>
		<pack name="Booster" id="64c5331a-b034-46a2-9134-5abf014c55c2">
			<options>
				<option probability="0.083">
					<pick qty="1" key="Rarity" value="Super Rare" />
					<pick qty="5" key="Rarity" value="Common" />
				</option>
				<option probability="0.250">
					<pick qty="1" key="Rarity" value="Very Rare" />
					<pick qty="5" key="Rarity" value="Common" />
				</option>
				<option probability="0.667">
					<pick qty="6" key="Rarity" value="Common" />
				</option>
			</options>
			<pick qty="1" key="Rarity" value="Rare" />
			<pick qty="3" key="Rarity" value="Uncommon"/>
		</pack>
	</packaging>
	<cards>
		<card name="Bolmeteus Black Dragon" id="805081a2-8861-424e-a2df-a6baf09a7ee6">
			<property name="Format" value="OCG" />
			<property name="Civilization" value="Darkness" />
			<property name="Cost" value="8" />
			<property name="Type" value="Creature" />
			<property name="Race" value="Armored Dragon/Demon Command" />
			<property name="Power" value="8000" />
			<property name="Rules" value="(This creature is put into your mana zone tapped)&#xd;&#xa;&#8203;Double breaker(This creature breaks 2 shields)&#xd;&#xa;When you put this creature into the battle zone, destroy one of your opponent's creatures.&#xd;&#xa;Whenever this creature would break a shield, your opponent puts that shield into their graveyard instead." />
			<property name="Rarity" value="No Rarity" />
			<property name="Number" value="1/37" />
		</card>
		<card name="Olzekia, General of Decapitation" id="61f468c3-e519-4c35-89ac-e952cc1d532b">
			<property name="Format" value="OCG" />
			<property name="Civilization" value="Darkness" />
			<property name="Cost" value="7" />
			<property name="Type" value="Creature" />
			<property name="Race" value="Demon Command" />
			<property name="Power" value="6000" />
			<property name="Rules" value="When you put this creature into the battle zone, destroy one of your creatures. Then your opponent chooses 2 of his creatures and destroys them.&#xd;&#xa;&#8203;Double breaker(This creature breaks 2 shields)" />
			<property name="Rarity" value="Super Rare" />
			<property name="Number" value="2/37" />
		</card>
		<card name="Bolmeteus Steel Dragon" id="e7300a94-201e-40a3-9039-8ed9d16d3a15">
			<property name="Format" value="OCG" />
			<property name="Civilization" value="Fire" />
			<property name="Cost" value="7" />
			<property name="Type" value="Creature" />
			<property name="Race" value="Armored Dragon" />
			<property name="Power" value="7000" />
			<property name="Rules" value="&#8203;Double breaker(This creature breaks 2 shields)&#xd;&#xa;Whenever this creature would break a shield, your opponent puts that shield into his graveyard instead." />
			<property name="Rarity" value="Super Rare" />
			<property name="Number" value="3/37" />
		</card>
		<card name="Bolmeteus Steel Dragon" id="7acf6a00-7e69-450d-b03f-c3445b266a91">
			<property name="Format" value="OCG" />
			<property name="Civilization" value="Fire" />
			<property name="Cost" value="7" />
			<property name="Type" value="Creature" />
			<property name="Race" value="Armored Dragon" />
			<property name="Power" value="7000" />
			<property name="Rules" value="&#8203;Double breaker(This creature breaks 2 shields)&#xd;&#xa;Whenever this creature would break a shield, your opponent puts that shield into his graveyard instead." />
			<property name="Rarity" value="Super Rare" />
			<property name="Number" value="3/37" />
		</card>
		<card name="Bolmeteus Steel Dragon" id="91babcb6-a85a-48ab-8a18-c34d158c8a2a">
			<property name="Format" value="OCG" />
			<property name="Civilization" value="Fire" />
			<property name="Cost" value="7" />
			<property name="Type" value="Creature" />
			<property name="Race" value="Armored Dragon" />
			<property name="Power" value="7000" />
			<property name="Rules" value="&#8203;Double breaker(This creature breaks 2 shields)&#xd;&#xa;Whenever this creature would break a shield, your opponent puts that shield into his graveyard instead." />
			<property name="Rarity" value="Super Rare" />
			<property name="Number" value="3/37" />
		</card>
		<card name="Perfect Galaxy, Spirit of Immortality" id="4548fc2c-7e9d-4edf-a56b-dc513f439e6f">
			<property name="Format" value="OCG" />
			<property name="Civilization" value="Light" />
			<property name="Cost" value="7" />
			<property name="Type" value="Creature" />
			<property name="Race" value="Angel Command" />
			<property name="Power" value="9000" />
			<property name="Rules" value="&#8203;Double breaker(This creature breaks 2 shields)&#xd;&#xa;Shield Force(When you put this creature into the battle zone, you may choose one of your shields. While the chosen shield remains in the shield zone, this creature gets the following  abilities)" />
			<property name="Rarity" value="Very Rare" />
			<property name="Number" value="6/37" />
		</card>
		<card name="Hanzou, Menacing Phantom" id="02669411-1f51-4767-968d-788861041d0c">
			<property name="Format" value="OCG" />
			<property name="Civilization" value="Darkness" />
			<property name="Cost" value="7" />
			<property name="Type" value="Creature" />
			<property name="Race" value="Demon Command/Shinobi" />
			<property name="Power" value="5000" />
			<property name="Rules" value="Ninja Strike 7(Whenever one of your opponent's creatures attacks or blocks, if you have 7 or more cards in your mana zone and if during that attack you didn't use a 'Ninja Strike' ability, you may summon this Shinobi for no cost. At the end of that turn, put this Shinobi on the bottom of your deck)&#xd;&#xa;When you put this creature into the battle zone, choose one of your opponent's creatures in the battle zone. That creature gets -6000 power until the end of the turn.&#xd;&#xa;When this creature would be destroyed and you have at least one darkness card in your mana zone, you may put one of your shields into your graveyard instead." />
			<property name="Rarity" value="Very Rare" />
			<property name="Number" value="7/37" />
		</card>
		<card name="Miraculous Snare" id="85b38bc2-4174-4f11-a7ae-a1120292aa7f">
			<property name="Format" value="OCG" />
			<property name="Civilization" value="Light" />
			<property name="Cost" value="3" />
			<property name="Type" value="Spell" />
			<property name="Race" value="" />
			<property name="Power" value="" />
			<property name="Rules" value="(This spell is put into your mana zone tapped)&#xd;&#xa;Choose a non-evolution creature in the battle zone and add it to its owner's shields face down." />
			<property name="Rarity" value="Very Rare" />
			<property name="Number" value="8/37" />
		</card>
		<card name="Bolmeteus Red Dragoon" id="7407cbb1-866c-45e3-a4b3-70c3c6b49f51">
			<property name="Format" value="OCG" />
			<property name="Civilization" value="Fire" />
			<property name="Cost" value="8" />
			<property name="Type" value="Creature" />
			<property name="Race" value="Tyranno Drake" />
			<property name="Power" value="9000" />
			<property name="Rules" value="&#8203;Double breaker(This creature breaks 2 shields)&#xd;&#xa;Whenever this creature would break a shield, your opponent puts that shield into their graveyard instead." />
			<property name="Rarity" value="No Rarity" />
			<property name="Number" value="9/37" />
		</card>
		<card name="Oracle Jewel of Control" id="823228d9-54f1-4988-a0a9-f9396282d50a">
			<property name="Format" value="OCG" />
			<property name="Civilization" value="Light" />
			<property name="Cost" value="8" />
			<property name="Type" value="Spell" />
			<property name="Race" value="" />
			<property name="Power" value="" />
			<property name="Rules" value="(This spell is put into your mana zone tapped)&#xd;&#xa;&#8203; Shield trigger(When this spell is put into your hand from your shield zone, you may cast it for no cost)&#xd;&#xa;Destroy one of your opponent's untapped creatures.&#xd;&#xa;Tap all your opponent's creatures in the battle zone." />
			<property name="Rarity" value="No Rarity" />
			<property name="Number" value="10/37" />
		</card>
		<card name="Bolmeteus White Flare" id="d8fe0283-6090-4c36-8e05-cf3ba1a0a1c6">
			<property name="Format" value="OCG" />
			<property name="Civilization" value="Light" />
			<property name="Cost" value="5" />
			<property name="Type" value="Spell" />
			<property name="Race" value="" />
			<property name="Power" value="" />
			<property name="Rules" value="(This spell is put into your mana zone tapped)&#xd;&#xa;&#8203; Shield trigger(When this spell is put into your hand from your shield zone, you may cast it for no cost)&#xd;&#xa;Choose one of the following. If you have a creature that has 'Bolmeteus' in its name in the battle zone, you may choose both." />
			<property name="Rarity" value="No Rarity" />
			<property name="Number" value="11/37" />
		</card>
		<card name="Rage Crystal of Outrage" id="51253c63-3ae9-4bd9-ac6a-f3731227bcdb">
			<property name="Format" value="OCG" />
			<property name="Civilization" value="Water" />
			<property name="Cost" value="8" />
			<property name="Type" value="Spell" />
			<property name="Race" value="" />
			<property name="Power" value="" />
			<property name="Rules" value="(This spell is put into your mana zone tapped)&#xd;&#xa;&#8203; Shield trigger(When this spell is put into your hand from your shield zone, you may cast it for no cost)&#xd;&#xa;Choose one of your opponent's creatures in the battle zone that has power 6000 or more and return it to its owner's hand. Then, destroy one of your opponent's creatures that has power 6000 or less." />
			<property name="Rarity" value="No Rarity" />
			<property name="Number" value="12/37" />
		</card>
		<card name="Legend of Hope and Victory" id="025d44e7-30d2-4c09-801b-0e8eb05e404b">
			<property name="Format" value="OCG" />
			<property name="Civilization" value="Water" />
			<property name="Cost" value="5" />
			<property name="Type" value="Spell" />
			<property name="Race" value="" />
			<property name="Power" value="" />
			<property name="Rules" value="(This spell is put into your mana zone tapped)&#xd;&#xa;Draw 2 cards. Then you may put a 'Bolmeteus Steel Dragon' from your hand into the battle zone." />
			<property name="Rarity" value="No Rarity" />
			<property name="Number" value="13/17" />
		</card>
		<card name="Perfect Madonna, Light Weapon" id="f2cb2e94-d728-4140-b53b-a8cd1714c95f">
			<property name="Format" value="OCG" />
			<property name="Civilization" value="Light" />
			<property name="Cost" value="5" />
			<property name="Type" value="Creature" />
			<property name="Race" value="Mecha Del Sol/Alien" />
			<property name="Power" value="2500" />
			<property name="Rules" value="&#8203; Blocker(Whenever an opponent's creature attacks, you may tap this creature to stop the attack. Then the 2 creatures battle)&#xd;&#xa;This creature can't attack players.&#xd;&#xa;When this creature would leave the battle zone, if this creature has more than 0 power, it stays in the battle zone instead." />
			<property name="Rarity" value="Rare" />
			<property name="Number" value="14/37" />
		</card>
		<card name="Chief De Baula, Machine King of Mystic Light" id="12d66e7b-867e-462e-a4de-3ebfd617f074">
			<property name="Format" value="OCG" />
			<property name="Civilization" value="Light" />
			<property name="Cost" value="4" />
			<property name="Type" value="Creature" />
			<property name="Race" value="Great Mecha King/Knight" />
			<property name="Power" value="4000" />
			<property name="Rules" value="&#8203; Blocker(Whenever an opponent's creature attacks, you may tap this creature to stop the attack. Then the 2 creatures battle)&#xd;&#xa;This creature can't attack players.&#xd;&#xa;When you put this creature into the battle zone, you may return a spell from your graveyard to your hand." />
			<property name="Rarity" value="Rare" />
			<property name="Number" value="15/37" />
		</card>
		<card name="Apocalypse Day" id="1c0b9cae-1475-48f9-917a-4fb50901aa45">
			<property name="Format" value="OCG" />
			<property name="Civilization" value="Light" />
			<property name="Cost" value="6" />
			<property name="Type" value="Spell" />
			<property name="Race" value="" />
			<property name="Power" value="" />
			<property name="Rules" value="&#8203; Shield trigger(When this spell is put into your hand from your shield zone, you may cast it for no cost)&#xd;&#xa;If there are 6 or more creatures in the battle zone, destroy all of them." />
			<property name="Rarity" value="Rare" />
			<property name="Number" value="16/37" />
		</card>
		<card name="DNA Spark" id="888d3e7d-a038-4179-95c5-feafdd6567fb">
			<property name="Format" value="OCG" />
			<property name="Civilization" value="Light" />
			<property name="Cost" value="6" />
			<property name="Type" value="Spell" />
			<property name="Race" value="" />
			<property name="Power" value="" />
			<property name="Rules" value="&#8203; Shield trigger(When this spell is put into your hand from your shield zone, you may cast it for no cost)&#xd;&#xa;Tap all your opponent's creatures in the battle zone.&#xd;&#xa;If you have 2 or less shields, add the top card of your deck to your shields face down." />
			<property name="Rarity" value="Rare" />
			<property name="Number" value="17/37" />
		</card>
		<card name="Vacuum Crawler" id="24f21120-e0cd-4b88-9220-2ee0f38aafaa">
			<property name="Format" value="OCG" />
			<property name="Civilization" value="Water" />
			<property name="Cost" value="5" />
			<property name="Type" value="Creature" />
			<property name="Race" value="Earth Eater" />
			<property name="Power" value="5000" />
			<property name="Rules" value="&#8203; Blocker(Whenever an opponent's creature attacks, you may tap this creature to stop the attack. Then the 2 creatures battle)&#xd;&#xa;This creature can't attack.&#xd;&#xa;At the start of your turn, return one of your creatures in the battle zone to their owner's hand. Then, you may draw a card." />
			<property name="Rarity" value="Rare" />
			<property name="Number" value="18/37" />
		</card>
		<card name="Crystal Memory" id="3effb905-1667-436b-9a06-eddd904e7577">
			<property name="Format" value="OCG" />
			<property name="Civilization" value="Water" />
			<property name="Cost" value="4" />
			<property name="Type" value="Spell" />
			<property name="Race" value="" />
			<property name="Power" value="" />
			<property name="Rules" value="&#8203; Shield trigger(When this spell is put into your hand from your shield zone, you may cast it for no cost)&#xd;&#xa;Search your deck. You may take a card from your deck and put it into your hand. Then shuffle your deck." />
			<property name="Rarity" value="Rare" />
			<property name="Number" value="19/37" />
		</card>
		<card name="Kareiko, Karma's Banned Technique" id="0c49d0bc-1f68-4261-a8cb-aa79ea2229dc">
			<property name="Format" value="OCG" />
			<property name="Civilization" value="Darkness" />
			<property name="Cost" value="3" />
			<property name="Type" value="Creature" />
			<property name="Race" value="Oracle" />
			<property name="Power" value="3000" />
			<property name="Rules" value="Whenever a card is put from a player's deck into a zone other than the hand, that player shuffles that card into their deck instead." />
			<property name="Rarity" value="Rare" />
			<property name="Number" value="20/37" />
		</card>
		<card name="Time Tripper, Shadow of Stagnation" id="073b0496-823b-40f3-89f2-8047bd8fa7c0">
			<property name="Format" value="OCG" />
			<property name="Civilization" value="Darkness" />
			<property name="Cost" value="3" />
			<property name="Type" value="Creature" />
			<property name="Race" value="Ghost" />
			<property name="Power" value="1000" />
			<property name="Rules" value="Your opponent's cards are put into their mana zone tapped." />
			<property name="Rarity" value="Rare" />
			<property name="Number" value="21/37" />
		</card>
		<card name="School Man" id="8aafae6d-0d67-43c5-90b7-3877b059816d">
			<property name="Format" value="OCG" />
			<property name="Civilization" value="Darkness" />
			<property name="Cost" value="2" />
			<property name="Type" value="Creature" />
			<property name="Race" value="Hedrian/Alien" />
			<property name="Power" value="8000" />
			<property name="Rules" value="&#8203;Double breaker(This creature breaks 2 shields)&#xd;&#xa;When you put this creature into the battle zone, destroy 2 of your creatures. Then your opponent chooses one of his creatures and destroys it." />
			<property name="Rarity" value="Rare" />
			<property name="Number" value="22/37" />
		</card>
		<card name="The Grave of Angels and Demons" id="217afe0e-a934-498d-a007-2a841f693656">
			<property name="Format" value="OCG" />
			<property name="Civilization" value="Light" />
			<property name="Cost" value="4" />
			<property name="Type" value="Spell" />
			<property name="Race" value="" />
			<property name="Power" value="" />
			<property name="Rules" value="(This spell is put into your mana zone tapped)&#xd;&#xa;&#8203; Shield trigger(When this spell is put into your hand from your shield zone, you may cast it for no cost)&#xd;&#xa;If there are 2 or more creatures that have the same name in the battle zone, destroy all of them. Then look at each player's mana zone. If there are 2 or more cards that have the same name, put all of them into their owner's graveyards." />
			<property name="Rarity" value="Rare" />
			<property name="Number" value="23/37" />
		</card>
		<card name="Olive Oil, Karma's Burial" id="7c37fd45-e909-4d49-90ee-e1201455b9ff">
			<property name="Format" value="OCG" />
			<property name="Civilization" value="Water" />
			<property name="Cost" value="5" />
			<property name="Type" value="Creature" />
			<property name="Race" value="Oracle/Great Mecha King" />
			<property name="Power" value="2000" />
			<property name="Rules" value="&#8203; Shield trigger(When this Card Type is put into your hand from your shield zone, you may use it for no cost)  &#8203; Blocker(Whenever an opponent's creature attacks, you may tap this creature to stop the attack. Then the 2 creatures battle)&#xd;&#xa;This creature can't attack.&#xd;&#xa;When you put this creature into the battle zone, choose a player. That player puts his graveyard into their deck and shuffles it." />
			<property name="Rarity" value="Uncommon" />
			<property name="Number" value="24/37" />
		</card>
		<card name="Ganveet Blaster" id="d8a308bf-4942-4582-8f60-052ed2bd436a">
			<property name="Format" value="OCG" />
			<property name="Civilization" value="Darkness" />
			<property name="Cost" value="7" />
			<property name="Type" value="Spell" />
			<property name="Race" value="" />
			<property name="Power" value="" />
			<property name="Rules" value="Destroy one of your opponent's creatures.&#xd;&#xa;Your opponent discards 2 cards from their hand." />
			<property name="Rarity" value="Uncommon" />
			<property name="Number" value="25/37" />
		</card>
		<card name="Moel, Love Sniper" id="3714e28f-40c1-4882-b67c-5b3dfd737b55">
			<property name="Format" value="OCG" />
			<property name="Civilization" value="Fire" />
			<property name="Cost" value="5" />
			<property name="Type" value="Creature" />
			<property name="Race" value="Human/Hunter/Alien" />
			<property name="Power" value="1000" />
			<property name="Rules" value="&#8203;  Shield trigger(When this creature is put into your hand from your shield zone, you may summon it for no cost)&#xd;&#xa;When you put this creature or a creature that costs 7 or more into the battle zone, destroy one of your opponent's creatures that has power 4000 or less." />
			<property name="Rarity" value="Uncommon" />
			<property name="Number" value="26/37" />
		</card>
		<card name="Berlin, Bell Gravekeeper" id="a25ef2ad-68db-4ed2-b0cd-547ae86d7462">
			<property name="Format" value="OCG" />
			<property name="Civilization" value="Light" />
			<property name="Cost" value="2" />
			<property name="Type" value="Creature" />
			<property name="Race" value="Initiate/Hedrian/Hunter" />
			<property name="Power" value="3000" />
			<property name="Rules" value="(This creature is put into your mana zone tapped)&#xd;&#xa;&#8203; Blocker(Whenever an opponent's creature attacks, you may tap this creature to stop the attack. Then the 2 creatures battle)&#xd;&#xa;This creature can't attack players.&#xd;&#xa;Whenever your opponent would choose a creature by a spell effect, they can't choose this one.&#xd;&#xa;Whenever a card is discarded by one of your opponent's spell effect or creature ability, you may return up to 2 cards from your graveyard to your hand." />
			<property name="Rarity" value="Uncommon" />
			<property name="Number" value="27/37" />
		</card>
		<card name="Hide and Seek" id="8bd03160-0e05-450d-95c5-cfda9f639caa">
			<property name="Format" value="OCG" />
			<property name="Civilization" value="Water" />
			<property name="Cost" value="4" />
			<property name="Type" value="Spell" />
			<property name="Race" value="" />
			<property name="Power" value="" />
			<property name="Rules" value="(This spell is put into your mana zone tapped)&#xd;&#xa;Choose one of your opponent's non-evolution creatures in the battle zone and return it to his hand. Then he discards a card at random from his hand." />
			<property name="Rarity" value="Uncommon" />
			<property name="Number" value="28/37" />
		</card>
		<card name="Persistent Prison of Gaia" id="5a6e7d69-1ae4-4c29-8467-5f52b9cdd53a">
			<property name="Format" value="OCG" />
			<property name="Civilization" value="Water" />
			<property name="Cost" value="5" />
			<property name="Type" value="Spell" />
			<property name="Race" value="" />
			<property name="Power" value="" />
			<property name="Rules" value="(This spell is put into your mana zone tapped)&#xd;&#xa;Choose one of your opponent's creatures in the battle zone and return it to its owner's hand. Then your opponent discards a card at random from their hand. If the discarded creature has the same name as the returned creature, choose one of your opponent's shields and put it into its owner's graveyard." />
			<property name="Rarity" value="Uncommon" />
			<property name="Number" value="29/37" />
		</card>
		<card name="Falconer, Lightfang Ninja" id="ade25afd-b52a-4815-b39a-f29f3a062006">
			<property name="Format" value="OCG" />
			<property name="Civilization" value="Light" />
			<property name="Cost" value="3" />
			<property name="Type" value="Creature" />
			<property name="Race" value="Guardian/Shinobi" />
			<property name="Power" value="3000" />
			<property name="Rules" value="Ninja Strike 4(Whenever one of your opponent's creatures attacks or blocks, if you have 4 or more cards in your mana zone and if during that attack you didn't use a 'Ninja Strike' ability, you may summon this Shinobi for no cost. At the end of that turn, put this Shinobi on the bottom of your deck)&#xd;&#xa;When you put this creature into the battle zone, one of your creatures gets 'blocker' until the start of your next turn." />
			<property name="Rarity" value="Common" />
			<property name="Number" value="30/37" />
		</card>
		<card name="Sol Habaki, Apocalyptic Sage" id="fb34fd17-a202-499c-a0b5-a165f3d367dd">
			<property name="Format" value="OCG" />
			<property name="Civilization" value="Light" />
			<property name="Cost" value="2" />
			<property name="Type" value="Creature" />
			<property name="Race" value="Light Bringer/Gladiator/Origin" />
			<property name="Power" value="1000" />
			<property name="Rules" value="When you put this creature into the battle zone, you may return a card from your mana zone to your hand. If you do, put a card from your hand into your mana zone." />
			<property name="Rarity" value="Common" />
			<property name="Number" value="31/37" />
		</card>
		<card name="Energy Stream" id="f23c3ff9-8987-47af-a790-2cc7fb5c4bdf">
			<property name="Format" value="OCG" />
			<property name="Civilization" value="Water" />
			<property name="Cost" value="3" />
			<property name="Type" value="Spell" />
			<property name="Race" value="" />
			<property name="Power" value="" />
			<property name="Rules" value="Draw 2 cards." />
			<property name="Rarity" value="Common" />
			<property name="Number" value="32/37" />
		</card>
		<card name="Hulcus Draw, Continuous Chant" id="de8b0e85-78a5-4264-a9b1-8402d602cf94">
			<property name="Format" value="OCG" />
			<property name="Civilization" value="Water" />
			<property name="Cost" value="2" />
			<property name="Type" value="Spell" />
			<property name="Race" value="" />
			<property name="Power" value="" />
			<property name="Rules" value="Draw a card.&#xd;&#xa;Recycle (You may pay  mana to cast this spell from your graveyard. After you cast, put this spell on the bottom of your deck)" />
			<property name="Rarity" value="Common" />
			<property name="Number" value="33/37" />
		</card>
		<card name="Spiral Gate" id="4a6cb98b-d298-4eb9-adae-e701fcc462ef">
			<property name="Format" value="OCG" />
			<property name="Civilization" value="Water" />
			<property name="Cost" value="2" />
			<property name="Type" value="Spell" />
			<property name="Race" value="" />
			<property name="Power" value="" />
			<property name="Rules" value="&#8203; Shield trigger(When this spell is put into your hand from your shield zone, you may cast it for no cost)&#xd;&#xa;Choose a creature in the battle zone and return it to its owner's hand." />
			<property name="Rarity" value="Common" />
			<property name="Number" value="34/37" />
		</card>
		<card name="Jenny, the Dismantling Puppet" id="dd05c0b7-02b5-411e-afa7-5514a40f3b96">
			<property name="Format" value="OCG" />
			<property name="Civilization" value="Darkness" />
			<property name="Cost" value="4" />
			<property name="Type" value="Creature" />
			<property name="Race" value="Death Puppet" />
			<property name="Power" value="1000" />
			<property name="Rules" value="When you put this creature into the battle zone, look at your opponent's hand and discard a card from it." />
			<property name="Rarity" value="Common" />
			<property name="Number" value="35/37" />
		</card>
		<card name="Bega, Vizier of Shadow" id="333101ad-f634-44a4-8c37-fd3f4283204f">
			<property name="Format" value="OCG" />
			<property name="Civilization" value="Light" />
			<property name="Cost" value="5" />
			<property name="Type" value="Creature" />
			<property name="Race" value="Initiate/Ghost" />
			<property name="Power" value="2000" />
			<property name="Rules" value="(This creature is put into your mana zone tapped)&#xd;&#xa;When you put this creature into the battle zone, add the top card of your deck to your shields face down. Then, discard a card at random from your opponent's hand." />
			<property name="Rarity" value="Common" />
			<property name="Number" value="36/37" />
		</card>
		<card name="Mil Armor, Mecha King Vizier" id="088e90f1-7640-47b8-ac34-d2d677c6f22d">
			<property name="Format" value="OCG" />
			<property name="Civilization" value="Light" />
			<property name="Cost" value="3" />
			<property name="Type" value="Creature" />
			<property name="Race" value="Great Mecha King/Initiate" />
			<property name="Power" value="3000" />
			<property name="Rules" value="(This creature is put into your mana zone tapped)&#xd;&#xa;&#8203; Blocker(Whenever an opponent's creature attacks, you may tap this creature to stop the attack. Then the 2 creatures battle)&#xd;&#xa;Your spells may each cost 1 less to cast. They can't cost less than 1." />
			<property name="Rarity" value="Common" />
			<property name="Number" value="37/37" />
		</card>

	</cards>
</set>
